httpy/__init__.py
httpy/alpn.py
httpy/cache.py
httpy/common.py
httpy/debugger.py
httpy/errors.py
httpy/headers.py
httpy/httpy.py
httpy/patterns.py
httpy/proto.py
httpy/response.py
httpy/ssl_context.py
httpy/status.py
httpy/stream.py
httpy/utils.py
httpy/http2/__init__.py
httpy/http2/connection.py
httpy/http2/error.py
httpy/http2/frame.py
httpy/http2/frame_queue.py
httpy/http2/priority.py
httpy/http2/proto.py
httpy/http2/settings.py
httpy/http2/socket_reader.py
httpy/http2/stream.py
httpy/http2/streams.py
httpy/http2/window.py
httpy/http2/hpack/__init__.py
httpy/http2/hpack/const.py
httpy/http2/hpack/errors.py
httpy/http2/hpack/hpack.py
httpy/http2/hpack/huffman.py
httpy/http2/hpack/integer.py
httpy/http2/hpack/table.py
httpy/http2/hpack/static/__huffman_table.py
httpy/http2/hpack/static/__init__.py
httpy/http2/hpack/static/__static_table.py
httpy/http2/hpack/utils/bitarray.py
httpy/http2/hpack/utils/stream_iterable.py
httpy-2.1.2.dist-info/LICENSE
httpy-2.1.2.dist-info/METADATA
httpy-2.1.2.dist-info/WHEEL
httpy-2.1.2.dist-info/top_level.txt
httpy-2.1.2.dist-info/RECORD
