Metadata-Version: 2.1
Name: httpy
Version: 2.1.2
Summary: A lightweight socket-based HTTP(s) and WebSocket client.
Author-email: Adam Jenca <jenca.a@gjh.sk>
License: GNU General Public License v3 (GPLv3)
Project-URL: Homepage, https://github.com/jenca-adam/httpy
Project-URL: Bug_Tracker, https://github.com/jenca-adam/httpy/issues
Project-URL: PyPI, https://pypi.python.org/project/httpy
Project-URL: Download, https://github.com/jenca-adam/httpy/releases/latest
Classifier: Development Status :: 4 - Beta
Classifier: Intended Audience :: Developers
Classifier: Operating System :: OS Independent
Classifier: Programming Language :: Python :: 3.6
Classifier: Programming Language :: Python :: 3.7
Classifier: Programming Language :: Python :: 3.8
Classifier: Programming Language :: Python :: 3.9
Classifier: Programming Language :: Python :: 3.10
Classifier: Programming Language :: Python :: 3.11
Classifier: Programming Language :: Python :: 3.12
Classifier: License :: OSI Approved :: GNU General Public License v3 (GPLv3)
Classifier: Topic :: Internet :: WWW/HTTP
Classifier: Environment :: Web Environment
Requires-Python: >=3.6.0
License-File: LICENSE
Provides-Extra: chardet
Requires-Dist: chardet; extra == "chardet"
